{
  "yID": 2023,
  "EMEA": {
    "AD": {
      "cName": "Andorra",
      "totalCount": 0,
      "totalAmount": 0
    },
    "AE": {
      "cName": "United Arab Emirates",
      "totalCount": 5,
      "totalAmount": 633.15
    },
    "AL": {
      "cName": "Albania",
      "totalCount": 9,
      "totalAmount": 1689
    },
    "AO": {
      "cName": "Angola",
      "totalCount": 1,
      "totalAmount": 222.81
    },
    "AX": {
      "cName": "Åland Islands",
      "totalCount": 0,
      "totalAmount": 0
    },
    "AZ": {
      "cName": "Azerbaijan",
      "totalCount": 0,
      "totalAmount": 0
    },
    "BA": {
      "cName": "Bosnia and Herzegovina",
      "totalCount": 8,
      "totalAmount": 101.98
    },
    "BE": {
      "cName": "Belgium",
      "totalCount": 154,
      "totalAmount": 26005.4297520661
    },
    "BG": {
      "cName": "Bulgaria",
      "totalCount": 24,
      "totalAmount": 4020.90833333333
    },
    "BL": {
      "cName": "Saint Barthélemy",
      "totalCount": 0,
      "totalAmount": 0
    },
    "BY": {
      "cName": "Belarus",
      "totalCount": 0,
      "totalAmount": 0
    },
    "CH": {
      "cName": "Switzerland",
      "totalCount": 102,
      "totalAmount": 26797.53
    },
    "CY": {
      "cName": "Cyprus",
      "totalCount": 7,
      "totalAmount": 1402.63865546218
    },
    "CZ": {
      "cName": "Czechia",
      "totalCount": 57,
      "totalAmount": 7800.8347107438
    },
    "DK": {
      "cName": "Denmark",
      "totalCount": 20,
      "totalAmount": 2234.064
    },
    "DZ": {
      "cName": "Algeria",
      "totalCount": 6,
      "totalAmount": 1751.49
    },
    "EE": {
      "cName": "Estonia",
      "totalCount": 2,
      "totalAmount": 436.5
    },
    "EG": {
      "cName": "Egypt",
      "totalCount": 1,
      "totalAmount": 94.98
    },
    "FI": {
      "cName": "Finland",
      "totalCount": 13,
      "totalAmount": 1307.79838709677
    },
    "FR": {
      "cName": "France",
      "totalCount": 712,
      "totalAmount": 97822.3
    },
    "GE": {
      "cName": "Georgia",
      "totalCount": 0,
      "totalAmount": 0
    },
    "GF": {
      "cName": "French Guiana",
      "totalCount": 0,
      "totalAmount": 0
    },
    "GG": {
      "cName": "Guernsey",
      "totalCount": 0,
      "totalAmount": 0
    },
    "GI": {
      "cName": "Gibralta",
      "totalCount": 1,
      "totalAmount": 112.5
    },
    "GP": {
      "cName": "Guadeloupe",
      "totalCount": 1,
      "totalAmount": 162.62
    },
    "GR": {
      "cName": "Greece",
      "totalCount": 38,
      "totalAmount": 6239.91935483871
    },
    "HR": {
      "cName": "Croatia",
      "totalCount": 58,
      "totalAmount": 11550.496
    },
    "HU": {
      "cName": "Hungary",
      "totalCount": 62,
      "totalAmount": 10936.0157480315
    },
    "IE": {
      "cName": "Ireland",
      "totalCount": 21,
      "totalAmount": 2955.06504065041
    },
    "IL": {
      "cName": "Israel",
      "totalCount": 7,
      "totalAmount": 2392.49
    },
    "IQ": {
      "cName": "Iraq",
      "totalCount": 0,
      "totalAmount": 0
    },
    "IS": {
      "cName": "Iceland",
      "totalCount": 2,
      "totalAmount": 1454.74
    },
    "JE": {
      "cName": "Jersey",
      "totalCount": 1,
      "totalAmount": 108.14
    },
    "JO": {
      "cName": "Jordan",
      "totalCount": 7,
      "totalAmount": 1320.76
    },
    "KW": {
      "cName": "Kuwait",
      "totalCount": 1,
      "totalAmount": 453.49
    },
    "KZ": {
      "cName": "Kazakhstan",
      "totalCount": 9,
      "totalAmount": 3166.9
    },
    "LB": {
      "cName": "Lebanon",
      "totalCount": 2,
      "totalAmount": 403.46
    },
    "LT": {
      "cName": "Lithuania",
      "totalCount": 10,
      "totalAmount": 1589.28099173554
    },
    "LU": {
      "cName": "Luxembourg",
      "totalCount": 10,
      "totalAmount": 2147.16239316239
    },
    "LV": {
      "cName": "Latvia",
      "totalCount": 11,
      "totalAmount": 1853.61157024793
    },
    "MA": {
      "cName": "Morocco",
      "totalCount": 0,
      "totalAmount": 0
    },
    "MC": {
      "cName": "Monaco",
      "totalCount": 2,
      "totalAmount": 473
    },
    "MD": {
      "cName": "Moldova, Republic of",
      "totalCount": 2,
      "totalAmount": 307.55
    },
    "ME": {
      "cName": "Montenegro",
      "totalCount": 1,
      "totalAmount": 113.39
    },
    "MF": {
      "cName": "Collectivity of Saint Martin",
      "totalCount": 2,
      "totalAmount": 211.83
    },
    "MG": {
      "cName": "Madagascar",
      "totalCount": 0,
      "totalAmount": 0
    },
    "MK": {
      "cName": "Macedonia, the former Yugoslav Republic of",
      "totalCount": 9,
      "totalAmount": 4253.8
    },
    "MQ": {
      "cName": "Martinique",
      "totalCount": 2,
      "totalAmount": 807.04
    },
    "MT": {
      "cName": "Malta",
      "totalCount": 14,
      "totalAmount": 3009.70338983051
    },
    "MU": {
      "cName": "Mauritius",
      "totalCount": 1,
      "totalAmount": 186.2
    },
    "MZ": {
      "cName": "Mozambique",
      "totalCount": 1,
      "totalAmount": 237.58
    },
    "NC": {
      "cName": "New Caledonia",
      "totalCount": 1,
      "totalAmount": 419.19
    },
    "NL": {
      "cName": "Netherlands",
      "totalCount": 133,
      "totalAmount": 24716.1983471074
    },
    "NO": {
      "cName": "Norway",
      "totalCount": 21,
      "totalAmount": 4327.4
    },
    "PF": {
      "cName": "French Polynesia",
      "totalCount": 41,
      "totalAmount": 6875.36
    },
    "PL": {
      "cName": "Poland",
      "totalCount": 8,
      "totalAmount": 2558.05691056911
    },
    "PT": {
      "cName": "Portugal",
      "totalCount": 13,
      "totalAmount": 2206.08
    },
    "QA": {
      "cName": "Qatar",
      "totalCount": 0,
      "totalAmount": 0
    },
    "RE": {
      "cName": "Réunion",
      "totalCount": 15,
      "totalAmount": 2444.57
    },
    "RO": {
      "cName": "Romania",
      "totalCount": 28,
      "totalAmount": 4631.0756302521
    },
    "RS": {
      "cName": "Serbia",
      "totalCount": 8,
      "totalAmount": 1635.46
    },
    "RU": {
      "cName": "Russian Federation",
      "totalCount": 0,
      "totalAmount": 0
    },
    "SA": {
      "cName": "Saudi Arabia",
      "totalCount": 1,
      "totalAmount": 263.32
    },
    "SE": {
      "cName": "Sweden",
      "totalCount": 37,
      "totalAmount": 5420.85365853658
    },
    "SI": {
      "cName": "Slovenia",
      "totalCount": 102,
      "totalAmount": 14528.737704918
    },
    "SK": {
      "cName": "Slovakia",
      "totalCount": 55,
      "totalAmount": 7569.825
    },
    "SZ": {
      "cName": "Swaziland",
      "totalCount": 1,
      "totalAmount": 329.29
    },
    "TF": {
      "cName": "French Southern Territories",
      "totalCount": 0,
      "totalAmount": 0
    },
    "TR": {
      "cName": "Turkey",
      "totalCount": 100,
      "totalAmount": 24674.97
    },
    "UA": {
      "cName": "Ukraine",
      "totalCount": 0,
      "totalAmount": 0
    },
    "UG": {
      "cName": "Uganda",
      "totalCount": 1,
      "totalAmount": 77.24
    },
    "IT": {
      "cName": "Mayotte",
      "totalCount": 1,
      "totalAmount": 388.61
    },
    "ZA": {
      "cName": "South Africa",
      "totalCount": 3,
      "totalAmount": 597.15
    }
  },
  "LATAM": {
    "AR": {
      "cName": "Argentina",
      "totalCount": 0,
      "totalAmount": 0
    },
    "AW": {
      "cName": "Aruba",
      "totalCount": 5,
      "totalAmount": 2450.28
    },
    "BM": {
      "cName": "Bermuda",
      "totalCount": 6,
      "totalAmount": 1752.53
    },
    "BR": {
      "cName": "Brazil",
      "totalCount": 8,
      "totalAmount": 1824.31
    },
    "CL": {
      "cName": "Cile",
      "totalCount": 9,
      "totalAmount": 2422.15
    },
    "CO": {
      "cName": "Colombia",
      "totalCount": 12,
      "totalAmount": 2014.78
    },
    "CR": {
      "cName": "Costa Rica",
      "totalCount": 1,
      "totalAmount": 244.98
    },
    "DM": {
      "cName": "Dominica",
      "totalCount": 0,
      "totalAmount": 0
    },
    "EC": {
      "cName": "Ecuador",
      "totalCount": 0,
      "totalAmount": 0
    },
    "LC": {
      "cName": "Saint Lucia",
      "totalCount": 0,
      "totalAmount": 0
    },
    "MX": {
      "cName": "Mexico",
      "totalCount": 23,
      "totalAmount": 7274.72
    },
    "PA": {
      "cName": "Panama",
      "totalCount": 0,
      "totalAmount": 0
    },
    "PR": {
      "cName": "Puerto Rico",
      "totalCount": 13,
      "totalAmount": 3994.07
    },
    "UY": {
      "cName": "Uruguay",
      "totalCount": 2,
      "totalAmount": 393.4
    },
    "VG": {
      "cName": "Virgin Islands, British",
      "totalCount": 0,
      "totalAmount": 0
    }
  },
  "APAC": {
    "BN": {
      "cName": "Brunei Darussalam",
      "totalCount": 6,
      "totalAmount": 2574.86
    },
    "HK": {
      "cName": "Hong Kong",
      "totalCount": 0,
      "totalAmount": 0
    },
    "ID": {
      "cName": "Indonesia",
      "totalCount": 7,
      "totalAmount": 3437.55
    },
    "IN": {
      "cName": "India",
      "totalCount": 2,
      "totalAmount": 785.03
    },
    "JP": {
      "cName": "Japan",
      "totalCount": 63,
      "totalAmount": 24649.03
    },
    "KH": {
      "cName": "Cambodia",
      "totalCount": 0,
      "totalAmount": 0
    },
    "KR": {
      "cName": "Korea, Republic of",
      "totalCount": 21,
      "totalAmount": 6650.17
    },
    "MY": {
      "cName": "Malaysia",
      "totalCount": 27,
      "totalAmount": 10304.76
    },
    "PH": {
      "cName": "Philippines",
      "totalCount": 20,
      "totalAmount": 5606.46
    },
    "SG": {
      "cName": "Singapore",
      "totalCount": 22,
      "totalAmount": 5575.47
    },
    "TH": {
      "cName": "Thailand",
      "totalCount": 21,
      "totalAmount": 5643.89
    },
    "VN": {
      "cName": "Vietnam",
      "totalCount": 6,
      "totalAmount": 2742.78
    }
  },
  "NA": {
    "CA": {
      "cName": "Canada",
      "totalCount": 13,
      "totalAmount": 1810.48
    },
    "US": {
      "cName": "United States of America",
      "totalCount": 122,
      "totalAmount": 34337.04
    }
  },
  "Others": {
    "XK": {
      "cName": "Kosovo",
      "totalCount": 3,
      "totalAmount": 495.19
    }
  }
}
